ffp2/__init__.py
ffp2/fingerprint.py
ffp2-0.1.dist-info/LICENSE
ffp2-0.1.dist-info/METADATA
ffp2-0.1.dist-info/WHEEL
ffp2-0.1.dist-info/top_level.txt
ffp2-0.1.dist-info/RECORD
