Metadata-Version: 2.1
Name: ffp2
Version: 0.1
Summary: File-Finger-Print generator 
Home-page: https://github.com/Ben-Bock/FFP2
Author: Ben Bock
Author-email: benbock@live.de
License: MIT License
Platform: any
Classifier: Development Status :: 4 - Beta
Classifier: Intended Audience :: Developers
Classifier: License :: OSI Approved :: MIT License
Classifier: Operating System :: OS Independent
Classifier: Programming Language :: Python
Classifier: Topic :: Software Development :: Libraries :: Python Modules
Requires-Python: >=3.0
